booth.v
`timescale 1ns / 1ps

module boothmultiplier(data_in,clk,start,result,done);
	
  wire ldA,clrA,sftA,ldQ,clrQ,sftQ;
  wire ldM,clrFF,addsub,decr,ldcount;
  input signed [15:0]data_in;
  input start,clk;
  wire qm1,eqz;
    output signed [31:0]result;
  output done;
  wire [4:0] countdata;
  wire signed [15:0] A,M,Q,Z;   //A->Acc , M->Multiplicand , Q->Multiplier, Z->(A-M,A+M) 
  assign eqz = ~| (countdata);
    assign result = {A,Q};

  shiftreg Acc_A(.data_out(A),
                 .ld_data(Z),
				 .s_in(A[15]),
				 .clk(clk),
				 .ld(ldA),
				 .rst(clrA),
				 .sft(sftA));
  
  
  
  shiftreg Mlpr_Q(.data_out(Q),
                .ld_data(data_in),
				.s_in(A[0]),
				.clk(clk),
				.ld(ldQ),
				.rst(clrQ),
				.sft(sftQ));
				
				
   dflipflop d_ff(.data_in(Q[0]),
                  .clk(clk),
				  .rst(clrFF),
				  .data_out(qm1));
				  
	
    PIPO Mlcd_M(.data_out(M),
                .data_in(data_in),
				.clk(clk),
				.ld(ldM));
				
	ALU  Adsub(.out(Z),
	           .in1(A),
			   .in2(M),
               .addsub(addsub));			
				
    bitcounter counter(.countdata(countdata),
	                   .decr(decr),
					   .ldcount(ldcount),
					   .clk(clk));
    
	controller fsm(.ldA(ldA),
	               .clrA(clrA),
				   .sftA(sftA),
				   .ldQ(ldQ),
				   .clrQ(clrQ),
				   .sftQ(sftQ),
				   .ldM(ldM),
				   .clrFF(clrFF),
                   .addsub(addsub),
				   .start(start),
				   .decr(decr),
				   .ldcount(ldcount),
				   .done(done),
				   .clk(clk),
				   .q0(Q[0]),
				   .qm1(qm1),
				   .eqz(eqz)); 

    endmodule


/////////////////////////////////////



module shiftreg(data_out,ld_data,s_in,clk,ld,rst,sft);   //SIPO

input [15:0] ld_data;
input clk,rst,ld,s_in,sft;
output reg [15:0]data_out;

always@(posedge clk)
 begin
    if(rst)
	    data_out <= 0;
	else if(ld)
        data_out <= ld_data;
    else if(sft)
        data_out <= {s_in,data_out[15:1]};	
 end
 
 endmodule

 //////////////

module dflipflop(data_in,clk,rst,data_out);

input data_in,clk,rst;
output reg data_out;

always@(posedge clk)
   begin
        if(rst)
		   data_out <= 0;
		else 
		   data_out <= data_in;
   end
   
endmodule   
////////////////

module PIPO(data_out,data_in,clk,ld);

input signed [15:0] data_in;
input clk,ld;
output reg signed [15:0] data_out;

always@(posedge clk)
  begin
      if(ld)
        data_out <= data_in;
   end
endmodule   

/////////////


module ALU (out,in1,in2,addsub);

  input addsub ;  // addsub = 1 then addition else subtraction
  input signed[15:0] in1,in2;
  output reg signed[15:0] out;
  
  always@(*)
    begin
      if(addsub)
	      out  = in1 + in2;
      else if(!addsub)
	      out  = in1 - in2;
	end
	
endmodule
	
/////////////////


module bitcounter(countdata,decr,ldcount,clk);
     input decr,ldcount,clk;
	 output reg [4:0] countdata;
	 
	 always@(posedge clk)
	   begin
	       if(ldcount)
		      countdata <= 16; //since datain is of 16 bits width
		   else if(decr)
              countdata <= countdata - 1;			
	   end
	   
endmodule
	 

//////////////////////////////////////////////////////////////////////////////////////



module controller(ldA,clrA,sftA,ldQ,clrQ,sftQ,ldM,clrFF,addsub,start,decr,
                     ldcount,done,clk,q0,qm1,eqz);
					 
    input clk,q0,qm1,start,eqz;
	output  ldA,clrA,sftA,ldQ,clrQ,sftQ,ldM,clrFF,addsub,decr,
                     ldcount,done;

	reg [2:0] state;
    parameter [2:0] S0 = 3'b000,
                    S1 = 3'b001,
					S2 = 3'b010,
					S3 = 3'b011,
					S4 = 3'b100,
					S5 = 3'b101,
					S6 = 3'b110;
					
	always@(posedge clk)
       begin
	        case(state)
			   S0 :  state = start?S1:S0;
			   S1 :  state = S2;
			   S2 :  begin
                     #1
			         if({q0,qm1}==2'b01)
					    state =  S3;
				     else if({q0,qm1}==2'b10)
					    state =  S4;
				     else if(({q0,qm1}==2'b00)||({q0,qm1}==2'b11))	
                        state =  S5;					 
                     end
					 
				S3 :  state =  S5;
				S4 :  state =  S5;
				S5 :  begin
                         #1 
				          if(({q0,qm1}==2'b01) && !eqz)
					         state =  S3;
				          else if(({q0,qm1}==2'b10) && !eqz)
							 state =  S4;
						  else if(eqz)
						     state = S6;    
				      end
				S6 :  state = S6;
				default : state <= S0;
			endcase	
		end	   
				
 
  
    assign ldA     = ((state == S3)||(state == S4))?1:0;
    assign clrA    =  (state == S0)?1:0;
	assign sftA    =  (state == S5)?1:0;
    assign ldQ     =  (state == S2)?1:0;
    assign clrQ    =  (state == S0)?1:0;
	assign sftQ    =  (state == S5)?1:0;
    assign ldM     =  (state == S1)?1:0;
    assign clrFF   =  (state == S0)?1:0;
	assign addsub     =  (state == S3)?1:0;
    
	assign decr    =  (state == S5)?1:0;
	assign ldcount =  (state == S1)?1:0; 
	assign done    =  (state == S6)?1:0;	
    
 
  endmodule

tb.v
`timescale 1ns / 1ps
module boothmultiplier_tb();
  reg [15:0] data_in;
  reg clk,start;
  wire [31:0] result;
  wire done;
  
  boothmultiplier dut(data_in,clk,start,result,done);
  
  initial
     begin
       clk = 0;
       forever #5 clk = ~clk;
     end
  
   
    
  initial
      begin
        
       
        @(negedge clk) start = 1;
        @(negedge clk) data_in = -10;
        @(negedge clk) data_in = 13;
   
        #500 $finish;
     end
  
    initial
      begin
        $monitor ($time, " Result: %d Done: %b", result,done);
        $dumpfile("boothmultiplier_tb.vcd");
        $dumpvars(0,boothmultiplier_tb);
      
      end
  
endmodule

boothmultiplier_tb.vcd
$date
	Sun Aug 18 19:24:42 2024
$end
$version
	Icarus Verilog
$end
$timescale
	1ps
$end
$scope module boothmultiplier_tb $end
$var wire 32 ! result [31:0] $end
$var wire 1 " done $end
$var reg 1 # clk $end
$var reg 16 $ data_in [15:0] $end
$var reg 1 % start $end
$scope module dut $end
$var wire 1 # clk $end
$var wire 16 & data_in [15:0] $end
$var wire 1 % start $end
$var wire 1 ' sftQ $end
$var wire 1 ( sftA $end
$var wire 32 ) result [31:0] $end
$var wire 1 * qm1 $end
$var wire 1 + ldcount $end
$var wire 1 , ldQ $end
$var wire 1 - ldM $end
$var wire 1 . ldA $end
$var wire 1 / eqz $end
$var wire 1 " done $end
$var wire 1 0 decr $end
$var wire 5 1 countdata [4:0] $end
$var wire 1 2 clrQ $end
$var wire 1 3 clrFF $end
$var wire 1 4 clrA $end
$var wire 1 5 addsub $end
$var wire 16 6 Z [15:0] $end
$var wire 16 7 Q [15:0] $end
$var wire 16 8 M [15:0] $end
$var wire 16 9 A [15:0] $end
$scope module Acc_A $end
$var wire 1 # clk $end
$var wire 1 : s_in $end
$var wire 1 ( sft $end
$var wire 1 4 rst $end
$var wire 16 ; ld_data [15:0] $end
$var wire 1 . ld $end
$var reg 16 < data_out [15:0] $end
$upscope $end
$scope module Adsub $end
$var wire 16 = in1 [15:0] $end
$var wire 16 > in2 [15:0] $end
$var wire 1 5 addsub $end
$var reg 16 ? out [15:0] $end
$upscope $end
$scope module Mlcd_M $end
$var wire 1 # clk $end
$var wire 16 @ data_in [15:0] $end
$var wire 1 - ld $end
$var reg 16 A data_out [15:0] $end
$upscope $end
$scope module Mlpr_Q $end
$var wire 1 # clk $end
$var wire 16 B ld_data [15:0] $end
$var wire 1 C s_in $end
$var wire 1 ' sft $end
$var wire 1 2 rst $end
$var wire 1 , ld $end
$var reg 16 D data_out [15:0] $end
$upscope $end
$scope module counter $end
$var wire 1 # clk $end
$var wire 1 + ldcount $end
$var wire 1 0 decr $end
$var reg 5 E countdata [4:0] $end
$upscope $end
$scope module d_ff $end
$var wire 1 # clk $end
$var wire 1 F data_in $end
$var wire 1 3 rst $end
$var reg 1 * data_out $end
$upscope $end
$scope module fsm $end
$var wire 1 # clk $end
$var wire 1 / eqz $end
$var wire 1 G q0 $end
$var wire 1 * qm1 $end
$var wire 1 % start $end
$var wire 1 ' sftQ $end
$var wire 1 ( sftA $end
$var wire 1 + ldcount $end
$var wire 1 , ldQ $end
$var wire 1 - ldM $end
$var wire 1 . ldA $end
$var wire 1 " done $end
$var wire 1 0 decr $end
$var wire 1 2 clrQ $end
$var wire 1 3 clrFF $end
$var wire 1 4 clrA $end
$var wire 1 5 addsub $end
$var parameter 3 H S0 $end
$var parameter 3 I S1 $end
$var parameter 3 J S2 $end
$var parameter 3 K S3 $end
$var parameter 3 L S4 $end
$var parameter 3 M S5 $end
$var parameter 3 N S6 $end
$var reg 3 O state [2:0] $end
$upscope $end
$upscope $end
$upscope $end
$enddefinitions $end
$comment Show the parameter values. $end
$dumpall
b110 N
b101 M
b100 L
b11 K
b10 J
b1 I
b0 H
$end
#0
$dumpvars
bx O
xG
xF
bx E
bx D
xC
bx B
bx A
bx @
bx ?
bx >
bx =
bx <
bx ;
x:
bx 9
bx 8
bx 7
bx 6
x5
x4
x3
x2
bx 1
x0
x/
x.
x-
x,
x+
x*
bx )
x(
x'
bx &
x%
bx $
0#
x"
bx !
$end
#5000
0.
14
0(
0,
12
0'
0-
13
05
00
0+
0"
b0 O
1#
#10000
1%
0#
#15000
0G
0F
0C
0:
0*
b0 7
b0 D
b0 !
b0 )
b0 9
b0 <
b0 =
04
02
1-
03
1+
b1 O
1#
#20000
b1111111111110110 $
b1111111111110110 &
b1111111111110110 @
b1111111111110110 B
0#
#25000
b1010 6
b1010 ;
b1010 ?
b1111111111110110 8
b1111111111110110 >
b1111111111110110 A
0/
b10000 1
b10000 E
1,
0-
0+
b10 O
1#
#30000
b1101 $
b1101 &
b1101 @
b1101 B
0#
#35000
1G
1F
b1101 !
b1101 )
b1101 7
b1101 D
1#
#36000
1.
0,
b100 O
#40000
0#
#45000
b10100 6
b10100 ;
b10100 ?
b10100000000000001101 !
b10100000000000001101 )
b1010 9
b1010 <
b1010 =
1*
0.
1(
1'
10
b101 O
1#
#50000
0#
#55000
0G
0F
b1111 6
b1111 ;
b1111 ?
1C
b1111 1
b1111 E
b110 7
b110 D
b1010000000000000110 !
b1010000000000000110 )
b101 9
b101 <
b101 =
1#
#56000
1.
b1111111111111011 6
b1111111111111011 ;
b1111111111111011 ?
0(
0'
15
00
b11 O
#60000
0#
#65000
1:
b11111111111110110000000000000110 !
b11111111111110110000000000000110 )
b1111111111111011 9
b1111111111111011 <
b1111111111111011 =
0*
0.
b101 6
b101 ;
b101 ?
1(
1'
05
10
b101 O
1#
#70000
0#
#75000
1G
1F
b111 6
b111 ;
b111 ?
b1110 1
b1110 E
b1000000000000011 7
b1000000000000011 D
b11111111111111011000000000000011 !
b11111111111111011000000000000011 )
b1111111111111101 9
b1111111111111101 <
b1111111111111101 =
1#
#76000
1.
0(
0'
00
b100 O
#80000
0#
#85000
b10001 6
b10001 ;
b10001 ?
0:
b1111000000000000011 !
b1111000000000000011 )
b111 9
b111 <
b111 =
1*
0.
1(
1'
10
b101 O
1#
#90000
0#
#95000
b1101 6
b1101 ;
b1101 ?
b1101 1
b1101 E
b1100000000000001 7
b1100000000000001 D
b111100000000000001 !
b111100000000000001 )
b11 9
b11 <
b11 =
1#
#100000
0#
#105000
b1011 6
b1011 ;
b1011 ?
0G
0F
b1 9
b1 <
b1 =
b11110000000000000 !
b11110000000000000 )
b1110000000000000 7
b1110000000000000 D
b1100 1
b1100 E
1#
#106000
1.
b1111111111110111 6
b1111111111110111 ;
b1111111111110111 ?
0(
0'
15
00
b11 O
#110000
0#
#115000
1:
0*
b11111111111101111110000000000000 !
b11111111111101111110000000000000 )
b1111111111110111 9
b1111111111110111 <
b1111111111110111 =
0.
b1 6
b1 ;
b1 ?
1(
1'
05
10
b101 O
1#
#120000
0#
#125000
b101 6
b101 ;
b101 ?
b1111111111111011 9
b1111111111111011 <
b1111111111111011 =
b11111111111110111111000000000000 !
b11111111111110111111000000000000 )
b1111000000000000 7
b1111000000000000 D
b1011 1
b1011 E
1#
#130000
0#
#135000
b111 6
b111 ;
b111 ?
b1010 1
b1010 E
b1111100000000000 7
b1111100000000000 D
b11111111111111011111100000000000 !
b11111111111111011111100000000000 )
b1111111111111101 9
b1111111111111101 <
b1111111111111101 =
1#
#140000
0#
#145000
b1000 6
b1000 ;
b1000 ?
0C
b1111111111111110 9
b1111111111111110 <
b1111111111111110 =
b11111111111111101111110000000000 !
b11111111111111101111110000000000 )
b1111110000000000 7
b1111110000000000 D
b1001 1
b1001 E
1#
#150000
0#
#155000
b1001 6
b1001 ;
b1001 ?
1C
b1000 1
b1000 E
b111111000000000 7
b111111000000000 D
b11111111111111110111111000000000 !
b11111111111111110111111000000000 )
b1111111111111111 9
b1111111111111111 <
b1111111111111111 =
1#
#160000
0#
#165000
b11111111111111111011111100000000 !
b11111111111111111011111100000000 )
b1011111100000000 7
b1011111100000000 D
b111 1
b111 E
1#
#170000
0#
#175000
b110 1
b110 E
b11111111111111111101111110000000 !
b11111111111111111101111110000000 )
b1101111110000000 7
b1101111110000000 D
1#
#180000
0#
#185000
b11111111111111111110111111000000 !
b11111111111111111110111111000000 )
b1110111111000000 7
b1110111111000000 D
b101 1
b101 E
1#
#190000
0#
#195000
b100 1
b100 E
b11111111111111111111011111100000 !
b11111111111111111111011111100000 )
b1111011111100000 7
b1111011111100000 D
1#
#200000
0#
#205000
b11111111111111111111101111110000 !
b11111111111111111111101111110000 )
b1111101111110000 7
b1111101111110000 D
b11 1
b11 E
1#
#210000
0#
#215000
b10 1
b10 E
b11111111111111111111110111111000 !
b11111111111111111111110111111000 )
b1111110111111000 7
b1111110111111000 D
1#
#220000
0#
#225000
b11111111111111111111111011111100 !
b11111111111111111111111011111100 )
b1111111011111100 7
b1111111011111100 D
b1 1
b1 E
1#
#230000
0#
#235000
1/
b0 1
b0 E
b11111111111111111111111101111110 !
b11111111111111111111111101111110 )
b1111111101111110 7
b1111111101111110 D
1#
#236000
0(
0'
00
1"
b110 O
